LICENSE
MANIFEST.in
README.md
setup.py
django_ws_include.egg-info/PKG-INFO
django_ws_include.egg-info/SOURCES.txt
django_ws_include.egg-info/dependency_links.txt
django_ws_include.egg-info/requires.txt
django_ws_include.egg-info/top_level.txt
ws_include/__init__.py
ws_include/checksum.py
ws_include/consumers.py
ws_include/crypto.py
ws_include/routing.py
ws_include/templates/ws_include/spinner.html
ws_include/templates/ws_include/template_tags/ws_include.html
ws_include/templatetags/__init__.py
ws_include/templatetags/ws_include.py
ws_include/templatetags/ws_included_length.py
ws_include/tests/__init__.py
ws_include/tests/base_test.py
ws_include/tests/settings.py
ws_include/tests/test_template_tag.py