Metadata-Version: 2.1
Name: django-ws-include
Version: 0.3.0
Summary: A simple application for Django to include (and fetch) asynchronous templates by loading templates with websocket connections.
Home-page: https://github.com/diegojromerolopez/django-ws-include
Author: Diego J. Romero López
Author-email: diegojromerolopez@gmail.com
License: MIT
Keywords: django template asynchronous template_tag websockets
Platform: UNKNOWN
Classifier: Programming Language :: Python :: Implementation :: CPython
Classifier: Development Status :: 5 - Production/Stable
Classifier: Framework :: Django
Classifier: License :: OSI Approved :: MIT License
Classifier: Programming Language :: Python :: 3.8
Classifier: Programming Language :: Python :: 3.9
Classifier: Programming Language :: Python :: 3.10
Classifier: Topic :: Software Development :: Libraries
License-File: LICENSE
